clean/__init__.py
clean/clean.py
clean_law-0.0.4.dist-info/LICENSE
clean_law-0.0.4.dist-info/METADATA
clean_law-0.0.4.dist-info/WHEEL
clean_law-0.0.4.dist-info/top_level.txt
clean_law-0.0.4.dist-info/RECORD
