Metadata-Version: 2.1
Name: clean-law
Version: 0.0.4
Summary: Generate Akoma Ntoso from Plain Text Laws
Home-page: https://github.com/lexpedite/clean
Author: Jason Morris
Author-email: jason@lexpedite.ca
License: MIT
Platform: UNKNOWN
Classifier: Development Status :: 3 - Alpha
Classifier: Intended Audience :: Legal Industry
Classifier: License :: OSI Approved :: MIT License
Classifier: Natural Language :: English
Classifier: Programming Language :: Python :: 3.8
Classifier: Topic :: Text Processing :: Markup
License-File: LICENSE
Requires-Dist: pyparsing (>=3.0.6)
Requires-Dist: pytest (>=5.4.3)
